har2requests/__init__.py
har2requests/request.py
har2requests/stringalg.py
har2requests/utils.py
har2requests-0.2.3.dist-info/LICENSE
har2requests-0.2.3.dist-info/METADATA
har2requests-0.2.3.dist-info/WHEEL
har2requests-0.2.3.dist-info/entry_points.txt
har2requests-0.2.3.dist-info/top_level.txt
har2requests-0.2.3.dist-info/RECORD
