Metadata-Version: 2.1
Name: har2requests
Version: 0.2.3
Summary: Generate Python Requests code from HAR file
Home-page: https://github.com/louisabraham/har2requests
Author: Louis Abraham
Author-email: louis.abraham@yahoo.fr
License: MIT
Platform: UNKNOWN
Classifier: Topic :: Internet :: WWW/HTTP
Classifier: Topic :: Software Development :: Code Generators
Classifier: Topic :: Utilities
Requires-Python: >=3.6
License-File: LICENSE
Requires-Dist: black
Requires-Dist: click
Requires-Dist: python-dateutil
Requires-Dist: tqdm
Provides-Extra: dev
Requires-Dist: wheel ; extra == 'dev'
